ansible_vault_manager/__init__.py
ansible_vault_manager/ansible_vault_manager.py
ansible_vault_manager/keyring_plugins/__init__.py
ansible_vault_manager/keyring_plugins/aws_ssm.py
ansible_vault_manager/keyring_plugins/bitwarden.py
ansible_vault_manager-0.2.3.dist-info/DESCRIPTION.rst
ansible_vault_manager-0.2.3.dist-info/METADATA
ansible_vault_manager-0.2.3.dist-info/RECORD
ansible_vault_manager-0.2.3.dist-info/WHEEL
ansible_vault_manager-0.2.3.dist-info/entry_points.txt
ansible_vault_manager-0.2.3.dist-info/metadata.json
ansible_vault_manager-0.2.3.dist-info/top_level.txt
