Metadata-Version: 2.0
Name: ansible-vault-manager
Version: 0.2.3
Summary: Python tool to manage Ansible vault-ids
Home-page: https://github.com/Smile-SA/ansible-vault-manager
Author: Guillaume GILL
Author-email: guillaume.gill@smile.fr
License: OSL
Platform: UNKNOWN
Classifier: Programming Language :: Python
Classifier: Programming Language :: Python :: 2.7
Classifier: Programming Language :: Python :: 3
Classifier: Programming Language :: Python :: 3.5
Classifier: Programming Language :: Python :: 3.6
Classifier: Programming Language :: Python :: 3.7
Classifier: Environment :: Console
Classifier: Intended Audience :: Developers
Classifier: Intended Audience :: Information Technology
Classifier: Intended Audience :: System Administrators
Classifier: Topic :: System :: Installation/Setup
Classifier: Topic :: System :: Systems Administration
Classifier: Topic :: Utilities
Requires-Python: >=2.7,!=3.0.*,!=3.1.*,!=3.2.*,!=3.3.*,!=3.4.*
Requires-Dist: future
Requires-Dist: PyYAML
